Metadata-Version: 2.1
Name: biomed-multi-view
Version: 1.1
Summary: This repository contains the implementation of the Multi-view Molecular Embedding with Late Fusion (MMELON) architecture.
Author-email: "Parthasarathy (Partha) Suryanarayanan" <psuryan@us.ibm.com>, Shreyans Sethi <shreyans.sethi@ibm.com>, Tim Rumbell <thrumbel@us.ibm.com>
Project-URL: repository, https://github.com/BiomedSciAI/biomed-multi-view
Requires-Python: <3.13,>=3.10
License-File: LICENSE
Requires-Dist: setuptools==69.5.1
Requires-Dist: torch==2.1.0
Requires-Dist: torchvision==0.16.0
Requires-Dist: fuse-med-ml==0.3.0
Requires-Dist: jsonargparse[signatures]==4.33.2
Requires-Dist: numpy==1.26.4
Requires-Dist: pandas==2.2.2
Requires-Dist: tqdm==4.66.5
Requires-Dist: rdkit-pypi==2022.9.5
Requires-Dist: regex==2024.9.11
Requires-Dist: biopython==1.84
Requires-Dist: datasets==2.12.0
Requires-Dist: pyarrow==12.0.0
Requires-Dist: openbabel-wheel==3.1.1.20
Requires-Dist: transformers==4.45.1
Requires-Dist: imageio==2.35.1
Requires-Dist: loralib==0.1.2
Requires-Dist: mplcursors==0.5.3
Requires-Dist: xgboost==2.0.3
Requires-Dist: joblib==1.3.2
Requires-Dist: x-transformers==1.27.19
Requires-Dist: lmdb==1.4.1
Requires-Dist: timm==0.9.16
Requires-Dist: litdata==0.2.6
Requires-Dist: torch_geometric==2.3.1
Requires-Dist: click==8.1.7
Requires-Dist: huggingface_hub==0.25.1
Provides-Extra: dev
Requires-Dist: jupyterlab==4.2.5; extra == "dev"
Requires-Dist: notebook==6.5.5; extra == "dev"
Requires-Dist: jupyter_nbextensions_configurator==0.6.4; extra == "dev"
Requires-Dist: nvitop==1.3.2; extra == "dev"
Requires-Dist: memory-profiler==0.61.0; extra == "dev"
Requires-Dist: seaborn==0.13.2; extra == "dev"
Requires-Dist: altair==5.4.1; extra == "dev"
Requires-Dist: umap-learn==0.5.6; extra == "dev"
Requires-Dist: exmol==3.0.3; extra == "dev"
Requires-Dist: nglview==3.0.8; extra == "dev"
Requires-Dist: pypdb==2.4; extra == "dev"
Requires-Dist: coverage==7.3.1; extra == "dev"
Requires-Dist: pytest==7.3.1; extra == "dev"
Requires-Dist: pytest-cov==4.1.0; extra == "dev"
